odoo/addons/pim/README.rst
odoo/addons/pim/__init__.py
odoo/addons/pim/__manifest__.py
odoo/addons/pim/data/ir_module_category_data.xml
odoo/addons/pim/i18n/pim.pot
odoo/addons/pim/readme/CONFIGURE.rst
odoo/addons/pim/readme/CONTRIBUTORS.rst
odoo/addons/pim/readme/DESCRIPTION.rst
odoo/addons/pim/readme/ROADMAP.rst
odoo/addons/pim/readme/USAGE.rst
odoo/addons/pim/security/pim_security.xml
odoo/addons/pim/static/description/icon.png
odoo/addons/pim/static/description/index.html
odoo/addons/pim/views/attribute_attribute.xml
odoo/addons/pim/views/attribute_group.xml
odoo/addons/pim/views/attribute_set.xml
odoo/addons/pim/views/pim_view.xml
odoo/addons/pim/views/product_view.xml
odoo13_addon_pim-13.0.1.0.2.dist-info/METADATA
odoo13_addon_pim-13.0.1.0.2.dist-info/WHEEL
odoo13_addon_pim-13.0.1.0.2.dist-info/top_level.txt
odoo13_addon_pim-13.0.1.0.2.dist-info/RECORD
