Metadata-Version: 2.1
Name: odoo13-addon-pim
Version: 13.0.1.0.2
Summary: Product Information Management
Home-page: https://github.com/OCA/odoo-pim
Author: Akretion,Odoo Community Association (OCA)
Author-email: support@odoo-community.org
License: AGPL-3
Platform: UNKNOWN
Classifier: Programming Language :: Python
Classifier: Framework :: Odoo
Classifier: License :: OSI Approved :: GNU Affero General Public License v3
Requires-Python: >=3.5
Requires-Dist: odoo13-addon-product-attribute-set
Requires-Dist: odoo13-addon-product-attribute-set-completeness
Requires-Dist: odoo (<13.1dev,>=13.0a)
